<?xml version="1.0" encoding="UTF-8"?>
<odoo>
	<template id="assets_backend" name="web_dialog_size assets"
		inherit_id="web.assets_backend">
		<xpath expr="." position="inside">
			<link rel="stylesheet" href="/web_ubiz_base/static/src/css/web_dialog_size.css" />
			<script type="text/javascript" src="/web_ubiz_base/static/src/js/web_dialog_size.js"></script>
		</xpath>
	</template>
	<template>
		<t t-extend="base.template">
		    <t t-jquery="span.o_mail_request_permission" t-operation="replace">
		        <li>new element</li>
		    </t>
		</t>
	</template>
</odoo>
